{
  "traditions": [
    "Медус",
    "Стихії",
    "Фераїс",
    "Лореліс",
    "Некромантія",
    "Сільферус",
    "Пентеони",
    "Обскурус",
    "Астрамантія",
    "Санґатус",
    "Геометрія",
    "Алхімія"
  ],
  "durationUnits": [
    {
      "value": "moment",
      "label": "Мить",
      "requiresValue": false
    },
    {
      "value": "rounds",
      "label": "Раунди",
      "requiresValue": true
    },
    {
      "value": "seconds",
      "label": "Секунди",
      "requiresValue": true
    },
    {
      "value": "minutes",
      "label": "Хвилини",
      "requiresValue": true
    },
    {
      "value": "hours",
      "label": "Години",
      "requiresValue": true
    },
    {
      "value": "until_short_rest",
      "label": "До короткого відпочинку",
      "requiresValue": false
    },
    {
      "value": "until_long_rest",
      "label": "До довгого відпочинку",
      "requiresValue": false
    },
    {
      "value": "custom",
      "label": "Власне значення",
      "requiresValue": false,
      "requiresCustomUnit": true
    }
  ],
  "spellLevels": {
    "min": 0,
    "max": 9
  },
  "actions": {
    "min": 1,
    "max": 3
  },
  "range": {
    "min": 0,
    "units": "Метри"
  },
  "defaultComponents": [],
  "flags": [
    {
      "name": "concentration",
      "label": "Зосередження"
    },
    {
      "name": "ritual",
      "label": "Ритуал"
    }
  ]
}